django_infosessions-1.1.dist-info/DESCRIPTION.rst
django_infosessions-1.1.dist-info/METADATA
django_infosessions-1.1.dist-info/RECORD
django_infosessions-1.1.dist-info/WHEEL
django_infosessions-1.1.dist-info/metadata.json
django_infosessions-1.1.dist-info/top_level.txt
infosessions/__init__.py
infosessions/admin.py
infosessions/constants.py
infosessions/middlewares.py
infosessions/models.py
infosessions/session.py
infosessions/settings.py
infosessions/migrations/0001_initial.py
infosessions/migrations/0002_auto_20150920_2302.py
infosessions/migrations/0003_auto_20150923_1219.py
infosessions/migrations/0004_rm_useragent.py
infosessions/migrations/__init__.py
tests/__init__.py
tests/test_settings.py
tests/tests.py
