Metadata-Version: 2.0
Name: django-infosessions
Version: 1.1
Summary: A simple Django app to capture session information
Home-page: UNKNOWN
Author: Aleksandr Razumov
Author-email: ar@cydev.ru
License: BSD License
Platform: UNKNOWN
Classifier: Environment :: Web Environment
Classifier: Framework :: Django
Classifier: Intended Audience :: Developers
Classifier: License :: OSI Approved :: BSD License
Classifier: Operating System :: OS Independent
Classifier: Programming Language :: Python
Classifier: Programming Language :: Python :: 2
Classifier: Programming Language :: Python :: 2.7
Classifier: Topic :: Internet :: WWW/HTTP
Classifier: Topic :: Internet :: WWW/HTTP :: Dynamic Content
Requires-Dist: django (>=1.8)
Requires-Dist: django-redis (>=3.8.3)
Requires-Dist: hiredis (>=0.1.4)
